httpxthrottlecache/__init__.py
httpxthrottlecache/_version.py
httpxthrottlecache/controller.py
httpxthrottlecache/httpxclientmanager.py
httpxthrottlecache/key_generator.py
httpxthrottlecache/ratelimiter.py
httpxthrottlecache/serializer.py
httpxthrottlecache/filecache/transport.py
httpxthrottlecache-0.2.1.dist-info/METADATA
httpxthrottlecache-0.2.1.dist-info/WHEEL
httpxthrottlecache-0.2.1.dist-info/licenses/LICENSE
httpxthrottlecache-0.2.1.dist-info/RECORD
