Metadata-Version: 2.4
Name: httpxthrottlecache
Version: 0.2.1
Summary: Rate Limiting and Caching HTTPX Client
Project-URL: Homepage, https://github.com/paultiq/httpxthrottlecache
Project-URL: Repository, https://github.com/paultiq/httpxthrottlecache
Project-URL: Issues, https://github.com/paultiq/httpxthrottlecache/issues
Author-email: Paul T <paul@iqmo.com>
License-File: LICENSE
Keywords: edgar,hishel,httpx,pyrate_limiter,sec
Classifier: Programming Language :: Python :: 3.10
Classifier: Programming Language :: Python :: 3.11
Classifier: Programming Language :: Python :: 3.12
Classifier: Programming Language :: Python :: 3.13
Classifier: Programming Language :: Python :: 3.14
Classifier: Programming Language :: Python :: Implementation :: PyPy
Requires-Python: >=3.10
Requires-Dist: aiofiles>=24.1.0
Requires-Dist: filelock>=3.18.0
Requires-Dist: hishel>=0.1.3
Requires-Dist: pyrate-limiter>=3.9.0
